CHANGELOG.txt
LICENCE.txt
MANIFEST.in
README.md
SM15K.egg-info/PKG-INFO
SM15K.egg-info/SOURCES.txt
SM15K.egg-info/dependency_links.txt
SM15K.egg-info/entry_points.txt
SM15K.egg-info/top_level.txt
deltaelektronika/SM15K.py
deltaelektronika/__init__.py
SM15K-0.0.7.dist-info/LICENCE.txt
SM15K-0.0.7.dist-info/METADATA
SM15K-0.0.7.dist-info/WHEEL
SM15K-0.0.7.dist-info/entry_points.txt
SM15K-0.0.7.dist-info/top_level.txt
SM15K-0.0.7.dist-info/RECORD
