Metadata-Version: 2.1
Name: SM15K
Version: 0.0.7
Summary: Delta Elektronika SM15K Power Supply Controller
Home-page: https://github.com/keklikyusuf/DeltaElektronika
Author: Yusuf Keklik
Author-email: keklikyusuf@gmail.com
License: MIT
Platform: UNKNOWN
Classifier: License :: OSI Approved :: MIT License
Classifier: Programming Language :: Python :: 3.6
Classifier: Programming Language :: Python :: 3.7
Classifier: Programming Language :: Python :: 3.8
License-File: LICENCE.txt
